<?xml version="1.0" encoding="utf-8"?>
<LanguageData>
  <!--The following translations were generated by https://www.deepl.com/-->
  <!-- EN: mecha drone -->
  <XFMParmor_Drone_Carrier.label>无人机</XFMParmor_Drone_Carrier.label>
  <!-- EN: A quad drone manufactured by carrier mechframe's internal forge. Accepts certain simple commands and will return to carrier when battery depletes. -->
  <XFMParmor_Drone_Carrier.description>由载具机械框架内部锻造制造的四轮无人机。可接受某些简单指令，并在电池耗尽时返回载具。</XFMParmor_Drone_Carrier.description>
  <!-- EN: left rotor blade -->
  <XFMParmor_Drone_Carrier.tools.left_rotor_blade.label>左旋翼</XFMParmor_Drone_Carrier.tools.left_rotor_blade.label>
  <!-- EN: right rotor blade -->
  <XFMParmor_Drone_Carrier.tools.right_rotor_blade.label>右旋翼</XFMParmor_Drone_Carrier.tools.right_rotor_blade.label>
</LanguageData>
